zhihu_qrcode_login/__init__.py
zhihu_qrcode_login/log_handler.py
zhihu_qrcode_login/login_handler.py
Zhihu_QRCode_Login-0.0.2.dist-info/LICENSE
Zhihu_QRCode_Login-0.0.2.dist-info/METADATA
Zhihu_QRCode_Login-0.0.2.dist-info/WHEEL
Zhihu_QRCode_Login-0.0.2.dist-info/top_level.txt
Zhihu_QRCode_Login-0.0.2.dist-info/RECORD
