Metadata-Version: 2.1
Name: Zhihu-QRCode-Login
Version: 0.0.2
Summary: One line to login Zhihu by QRCode.
Home-page: https://github.com/Crawler995/ZhihuQRCodeLogin
Author: crawler995
Author-email: zhang_995@foxmail.com
License: MIT
Keywords: Zhihu,login
Platform: UNKNOWN
Requires-Dist: requests
Requires-Dist: matplotlib
